speculos/__init__.py
speculos/__main__.py
speculos/__version__.py
speculos/client.py
speculos/main.py
speculos/observer.py
speculos/resources_importer.py
speculos/api/README.md
speculos/api/__init__.py
speculos/api/apdu.py
speculos/api/api.py
speculos/api/automation.py
speculos/api/button.py
speculos/api/events.py
speculos/api/finger.py
speculos/api/restful.py
speculos/api/screenshot.py
speculos/api/swagger.py
speculos/api/swagger.yaml
speculos/api/ticker.py
speculos/api/web_interface.py
speculos/api/resources/apdu.schema
speculos/api/resources/button.schema
speculos/api/resources/finger.schema
speculos/api/resources/ticker.schema
speculos/api/static/index.html
speculos/api/static/swagger/README.md
speculos/api/static/swagger/favicon-16x16.png
speculos/api/static/swagger/favicon-32x32.png
speculos/api/static/swagger/index.html
speculos/api/static/swagger/swagger-ui-bundle.js
speculos/api/static/swagger/swagger-ui-standalone-preset.js
speculos/api/static/swagger/swagger-ui.css
speculos/api/static/swagger/swagger.json
speculos/cxlib/flex-api-level-cx-22.elf
speculos/cxlib/nanosp-api-level-cx-22.elf
speculos/cxlib/nanox-api-level-cx-22.elf
speculos/cxlib/stax-api-level-cx-22.elf
speculos/fonts/flex-fonts-18.bin
speculos/fonts/flex-fonts-19.bin
speculos/fonts/flex-fonts-20.bin
speculos/fonts/flex-fonts-21.bin
speculos/fonts/flex-fonts-22.bin
speculos/fonts/nanosp-fonts-18.bin
speculos/fonts/nanosp-fonts-22.bin
speculos/fonts/nanox-fonts-18.bin
speculos/fonts/nanox-fonts-22.bin
speculos/fonts/stax-fonts-1.bin
speculos/fonts/stax-fonts-10.bin
speculos/fonts/stax-fonts-11.bin
speculos/fonts/stax-fonts-12.bin
speculos/fonts/stax-fonts-13.bin
speculos/fonts/stax-fonts-14.bin
speculos/fonts/stax-fonts-15.bin
speculos/fonts/stax-fonts-20.bin
speculos/fonts/stax-fonts-21.bin
speculos/fonts/stax-fonts-22.bin
speculos/fonts/stax-fonts-3.bin
speculos/fonts/stax-fonts-5.bin
speculos/fonts/stax-fonts-7.bin
speculos/fonts/stax-fonts-8.bin
speculos/fonts/stax-fonts-9.bin
speculos-0.25.13.dist-info/licenses/COPYING
speculos-0.25.13.dist-info/licenses/COPYING.LESSER
speculos-0.25.13.dist-info/METADATA
speculos-0.25.13.dist-info/WHEEL
speculos-0.25.13.dist-info/entry_points.txt
speculos-0.25.13.dist-info/top_level.txt
speculos-0.25.13.dist-info/RECORD
