Metadata-Version: 2.4
Name: speculos
Version: 0.25.13
Summary: Ledger Stax, Flex, Apex+ and Nano S+/X application emulator
Author-email: Ledger <hello@ledger.fr>
Project-URL: Homepage, https://github.com/LedgerHQ/speculos
Project-URL: Bug Tracker, https://github.com/LedgerHQ/speculos/issues
Classifier: Programming Language :: Python :: 3
Classifier: Programming Language :: Python :: 3.9
Classifier: Programming Language :: Python :: 3.10
Classifier: Programming Language :: Python :: 3.11
Classifier: Programming Language :: Python :: 3.12
Classifier: Programming Language :: Python :: 3.13
Classifier: License :: OSI Approved :: GNU General Public License v3 (GPLv3)
Classifier: Operating System :: POSIX :: Linux
Classifier: Operating System :: MacOS :: MacOS X
Requires-Python: >=3.10
License-File: COPYING
License-File: COPYING.LESSER
Requires-Dist: construct<3.0.0,>=2.10.56
Requires-Dist: flask<3.0.0,>=2.0.0
Requires-Dist: flask-restful<1.0,>=0.3.9
Requires-Dist: flask-cors<7.0.0,>=5.0.0
Requires-Dist: jsonschema<4.18.0,>=3.2.0
Requires-Dist: mnemonic<1.0,>=0.19
Requires-Dist: pillow<11.0.0,>=8.0.0
Requires-Dist: pyelftools<1.0,>=0.27
Requires-Dist: pyqt6<7.0.0,>=6.4.0
Requires-Dist: requests<3.0.0,>=2.25.1
Requires-Dist: ledgered>=0.14.0
Requires-Dist: pygame>=2.6.1
Provides-Extra: dev
Requires-Dist: pytest; extra == "dev"
Requires-Dist: pytest-cov; extra == "dev"
Dynamic: license-file
